{
  "spectra": [
    {
      "data": {},
      "id": "0abwvynpah97",
      "source": {
        "original": [],
        "jcamp": null,
        "jcampURL": "./01-05-02/1h.jdx"
      },
      "display": {
        "name": "1H RMN",
        "color": "#C10020"
      }
    }
  ],
  "molecules": [
    {
      "molfile": "\nActelion Java MolfileCreator 1.0\n\n 13 12  0  0  0  0  0  0  0  0999 V2000\n    4.1480   -5.1052   -0.0000 C   0  0  0  0  0  0  0  0  0  0  0  0\n    5.6477   -5.1371   -0.0000 C   0  0  0  0  0  0  0  0  0  0  0  0\n    6.9467   -4.3871   -0.0000 C   0  0  0  0  0  0  0  0  0  0  0  0\n    8.2457   -5.1371   -0.0000 C   0  0  0  0  0  0  0  0  0  0  0  0\n    6.9467   -2.8871   -0.0000 O   0  0  0  0  0  0  0  0  0  0  0  0\n    3.6424   -4.1849   -0.0000 H   0  0  0  0  0  0  0  0  0  0  0  0\n    3.6038   -6.0032   -0.0000 H   0  0  0  0  0  0  0  0  0  0  0  0\n    5.7481   -5.5281   -0.0000 H   0  0  0  0  0  0  0  0  0  0  0  0\n    6.9467   -5.1371   -0.0000 H   0  0  0  0  0  0  0  0  0  0  0  0\n    9.1550   -5.6621   -0.0000 H   0  0  0  0  0  0  0  0  0  0  0  0\n    7.7207   -6.0464   -0.0000 H   0  0  0  0  0  0  0  0  0  0  0  0\n    8.7707   -4.2278   -0.0000 H   0  0  0  0  0  0  0  0  0  0  0  0\n    5.8860   -1.8264   -0.0000 H   0  0  0  0  0  0  0  0  0  0  0  0\n  1  2  2  0  0  0  0\n  2  3  1  0  0  0  0\n  3  4  1  0  0  0  0\n  3  5  1  0  0  0  0\n  1  6  1  0  0  0  0\n  1  7  1  0  0  0  0\n  2  8  1  0  0  0  0\n  3  9  1  1  0  0  0\n  4 10  1  0  0  0  0\n  4 11  1  0  0  0  0\n  4 12  1  0  0  0  0\n  5 13  1  0  0  0  0\nM  END\n"
    }
  ]
}
